{
  "type": "minecraft:chest",
  "pools": [
    {
      "bonus_rolls": 0.0,
      "entries": [
        {
          "type": "minecraft:item",
          "name": "minecraft:diamond_sword"
        },
        {
          "type": "minecraft:item",
          "name": "minecraft:iron_sword",
          "weight": 3
        },
        {
          "type": "minecraft:item",
          "name": "minecraft:bow",
          "weight": 3
        },
        {
          "type": "minecraft:item",
          "name": "minecraft:crossbow",
          "weight": 2
        },
        {
          "type": "minecraft:item",
          "name": "minecraft:shield",
          "weight": 2
        },
        {
          "type": "minecraft:item",
          "functions": [
            {
              "add": false,
              "count": {
                "type": "minecraft:uniform",
                "max": 24.0,
                "min": 8.0
              },
              "function": "minecraft:set_count"
            }
          ],
          "name": "minecraft:arrow",
          "weight": 4
        },
        {
          "type": "minecraft:item",
          "name": "minecraft:iron_axe",
          "weight": 2
        },
        {
          "type": "minecraft:empty",
          "weight": 6
        }
      ],
      "rolls": 1.0
    }
  ],
  "random_sequence": "sbuild:chests/high_2"
}